nornir_rich/__init__.py
nornir_rich/functions.py
nornir_rich/processor.py
nornir_rich/progress_bar.py
nornir_rich-0.2.0.dist-info/METADATA
nornir_rich-0.2.0.dist-info/WHEEL
nornir_rich-0.2.0.dist-info/RECORD
