Metadata-Version: 2.1
Name: nornir-rich
Version: 0.2.0
Summary: Collection of 'nice looking' functions with rich for nornir
Home-page: https://github.com/InfrastructureAsCode-ch/nornir_rich
License: Apache-2.0
Author: ubaumann
Author-email: github@m.ubaumann.ch
Requires-Python: >=3.8,<4.0
Classifier: License :: OSI Approved :: Apache Software License
Classifier: Programming Language :: Python :: 3
Classifier: Programming Language :: Python :: 3.8
Classifier: Programming Language :: Python :: 3.9
Classifier: Programming Language :: Python :: 3.10
Classifier: Programming Language :: Python :: 3.11
Classifier: Programming Language :: Python :: 3.12
Requires-Dist: nornir (>=3,<4)
Requires-Dist: rich (>=12,<14)
Project-URL: Repository, https://github.com/InfrastructureAsCode-ch/nornir_rich
